Ardy-0.0.2.dist-info/DESCRIPTION.rst
Ardy-0.0.2.dist-info/METADATA
Ardy-0.0.2.dist-info/RECORD
Ardy-0.0.2.dist-info/WHEEL
Ardy-0.0.2.dist-info/entry_points.txt
Ardy-0.0.2.dist-info/metadata.json
Ardy-0.0.2.dist-info/top_level.txt
Ardy-0.0.2.dist-info/zip-safe
ardy/__init__.py
ardy/config/__init__.py
ardy/config/exceptions.py
ardy/core/__init__.py
ardy/core/exceptions.py
ardy/core/build/__init__.py
ardy/core/build/build.py
ardy/core/cmd/__init__.py
ardy/core/cmd/main.py
ardy/core/deploy/__init__.py
ardy/core/deploy/deploy.py
ardy/core/invoke/__init__.py
ardy/core/invoke/invoke.py
ardy/core/triggers/__init__.py
ardy/core/triggers/driver.py
ardy/core/triggers/exceptions.py
ardy/core/triggers/cloudwatchevent/__init__.py
ardy/core/triggers/s3/__init__.py
ardy/core/triggers/sns/__init__.py
ardy/template/__init__.py
ardy/utils/__init__.py
ardy/utils/aws.py
ardy/utils/log.py
examples/__init__.py
tests/__init__.py
tests/mocks_utils.py
tests/test_build.py
tests/test_cmd.py
tests/test_config.py
tests/test_deploy_integration.py
tests/test_deploy_unit.py
tests/test_invoke.py
tests/utils.py
tests/myexamplelambdaproject/__init__.py
tests/myexamplelambdaproject/main.py
tests/myexamplelambdaproject/lambda1/__init__.py
tests/myexamplelambdaproject/lambda1/main.py
tests/myexamplelambdaproject/lambda2/__init__.py
tests/myexamplelambdaproject/lambda2/main.py
