Metadata-Version: 2.0
Name: Ardy
Version: 0.0.2
Summary: AWS Lambda toolkit
Home-page: https://github.com/avara1986/ardy.git
Author: Alberto Vara
Author-email: a.vara.1986@gmail.com
License: MIT
Keywords: python,aws,lambda
Platform: any
Classifier: Development Status :: 4 - Beta
Classifier: Environment :: Console
Classifier: Intended Audience :: Developers
Classifier: Intended Audience :: System Administrators
Classifier: Natural Language :: English
Classifier: License :: OSI Approved :: MIT License
Classifier: Operating System :: OS Independent
Classifier: Programming Language :: Python
Classifier: Programming Language :: Python :: 2.7
Classifier: Programming Language :: Python :: 3.3
Classifier: Programming Language :: Python :: 3.6
Requires-Dist: boto3 (>=1.4.4)
